pirogue_admin_api/__init__.py
pirogue_admin_api/network_pb2.py
pirogue_admin_api/network_pb2.pyi
pirogue_admin_api/network_pb2_grpc.py
pirogue_admin_api/services_pb2.py
pirogue_admin_api/services_pb2.pyi
pirogue_admin_api/services_pb2_grpc.py
pirogue_admin_api/system_pb2.py
pirogue_admin_api/system_pb2.pyi
pirogue_admin_api/system_pb2_grpc.py
pirogue_admin_api-2.0.2.dist-info/licenses/LICENSE
pirogue_admin_api-2.0.2.dist-info/METADATA
pirogue_admin_api-2.0.2.dist-info/WHEEL
pirogue_admin_api-2.0.2.dist-info/top_level.txt
pirogue_admin_api-2.0.2.dist-info/RECORD
