Metadata-Version: 2.4
Name: pirogue-admin-api
Version: 2.0.2
Summary: API definition of the communication protocol between the administration client and daemon for PiRogue.
Author-email: Christophe Andral <christophe@andral.fr>
Maintainer-email: U+039b <hello@pts-project.org>
License-Expression: GPL-3.0+
Project-URL: repository, https://github.com/PiRogueToolSuite/pirogue-admin
Project-URL: issues, https://github.com/PiRogueToolSuite/pirogue-admin/issues
Requires-Python: >=3.9
License-File: LICENSE
Requires-Dist: grpcio
Requires-Dist: pyyaml
Dynamic: license-file
